README
code-guide
setup.py
code_guide/__init__.py
code_guide/bootstro.css
code_guide/bootstro.js
code_guide/bootstro.min.css
code_guide/bootstro.min.js
code_guide/code-guide.css
code_guide/code-guide.js
code_guide/jquery-1.9.1.js
code_guide/jquery-1.9.1.min.js
code_guide/pygments.css
code_guide/test_code_guide.py
code_guide.egg-info/PKG-INFO
code_guide.egg-info/SOURCES.txt
code_guide.egg-info/dependency_links.txt
code_guide.egg-info/requires.txt
code_guide.egg-info/top_level.txt