Metadata-Version: 1.1
Name: code-guide
Version: 1.0.2
Summary: Turn example code into interactive HTML documentation
Home-page: http://natpryce.com
Author: Nat Pryce
Author-email: sw@natpryce.com
License: Apache 2.0. Bootstro is used under the MIT license.
Platform: UNKNOWN
Classifier: Development Status :: 4 - Beta
Classifier: Environment :: Console
Classifier: Intended Audience :: Developers
Classifier: License :: OSI Approved :: Apache Software License
Classifier: License :: OSI Approved :: MIT License
Classifier: Programming Language :: Python
Classifier: Programming Language :: Python :: 2
Classifier: Natural Language :: English
Classifier: Topic :: Software Development
Provides: code_guide
